scripts/__init__.py
scripts/setup_app_and_key.py
yaml2workflow/__init__.py
yaml2workflow/validator.py
yaml2workflow/converter/__init__.py
yaml2workflow/converter/model.py
yaml2workflow/exporter/__init__.py
yaml2workflow/exporter/workflow.py
yaml2workflow/parser/__init__.py
yaml2workflow/parser/model.py
yaml2workflow/parser/workflow.py
yaml2workflow-0.2.4.dist-info/LICENSE
yaml2workflow-0.2.4.dist-info/METADATA
yaml2workflow-0.2.4.dist-info/WHEEL
yaml2workflow-0.2.4.dist-info/top_level.txt
yaml2workflow-0.2.4.dist-info/RECORD
