Metadata-Version: 2.1
Name: yaml2workflow
Version: 0.2.4
Summary: Manage and create Clarifai workflows with yaml files
Home-page: https://github.com/isaac-chung/yaml2workflow
Author: Isaac Chung
Author-email: chungisaac1217@gmail.com
License: MIT
Requires-Python: >=3.7
License-File: LICENSE
Requires-Dist: clarifai-grpc (>=8.11.0)
